[{"ph":"X","cat":"cpu_op","name":"aten::zeros","pid":8,"tid":8,"ts":1678058059302600,"dur":4},{"ph":"X","cat":"cpu_op","name":"aten::empty","pid":8,"tid":8,"ts":1678058059302601,"dur":1},{"ph":"X","cat":"cpu_op","name":"aten::zero_","pid":8,"tid":8,"ts":1678058059302603,"dur":1},{"ph":"X","cat":"cpu_op","name":"aten::empty","pid":8,"tid":8,"ts":1678058059302610,"dur":1},{"ph":"X","cat":"cpu_op","name":"aten::zeros","pid":8,"tid":8,"ts":1678058059302718,"dur":4},{"ph":"X","cat":"cpu_op","name":"aten::empty","pid":8,"tid":8,"ts":1678058059302719,"dur":1},{"ph":"X","cat":"cpu_op","name":"aten::zero_","pid":8,"tid":8,"ts":1678058059302721,"dur":0},{"ph":"X","cat":"cpu_op","name":"aten::empty","pid":8,"tid":8,"ts":1678058059302727,"dur":1},{"ph":"X","cat":"cpu_op","name":"aten::linear","pid":8,"tid":8,"ts":1678058059302738,"dur":78},{"ph":"X","cat":"cpu_op","name":"aten::t","pid":8,"tid":8,"ts":1678058059302739,"dur":8},{"ph":"X","cat":"cpu_op","name":"aten::transpose","pid":8,"tid":8,"ts":1678058059302742,"dur":3},{"ph":"X","cat":"cpu_op","name":"aten::as_strided","pid":8,"tid":8,"ts":1678058059302744,"dur":1},{"ph":"X","cat":"cpu_op","name":"aten::view","pid":8,"tid":8,"ts":1678058059302748,"dur":3},{"ph":"X","cat":"cpu_op","name":"aten::addmm","pid":8,"tid":8,"ts":1678058059302752,"dur":59},{"ph":"X","cat":"cpu_op","name":"aten::empty","pid":8,"tid":8,"ts":1678058059302768,"dur":12},{"ph":"X","cat":"cuda_runtime","name":"cudaOccupancyMaxActiveBlocksPerMultiprocessorWithFlags","pid":8,"tid":8,"ts":1678058059302791,"dur":1},{"ph":"X","cat":"cuda_runtime","name":"cudaLaunchKernel","pid":8,"tid":8,"ts":1678058059302796,"dur":10},{"ph":"X","cat":"cpu_op","name":"aten::view","pid":8,"tid":8,"ts":1678058059302813,"dur":3},{"ph":"X","cat":"kernel","name":"ampere_sgemm_128x64_tn","pid":0,"tid":7,"ts":1678058059323577,"dur":3376}]