[{"ph":"X","cat":"cpu_op","name":"autograd::engine::evaluate_function: TransposeBackward0","pid":7,"tid":395,"ts":1677893021977653,"dur":8},{"ph":"X","cat":"cpu_op","name":"TransposeBackward0","pid":7,"tid":395,"ts":1677893021977654,"dur":5},{"ph":"X","cat":"cpu_op","name":"aten::transpose","pid":7,"tid":395,"ts":1677893021977655,"dur":3},{"ph":"X","cat":"cpu_op","name":"aten::as_strided","pid":7,"tid":395,"ts":1677893021977656,"dur":1},{"ph":"X","cat":"cpu_op","name":"autograd::engine::evaluate_function: ViewBackward0","pid":7,"tid":395,"ts":1677893021977664,"dur":53},{"ph":"X","cat":"cpu_op","name":"ViewBackward0","pid":7,"tid":395,"ts":1677893021977665,"dur":48},{"ph":"X","cat":"cpu_op","name":"aten::reshape","pid":7,"tid":395,"ts":1677893021977666,"dur":47},{"ph":"X","cat":"cpu_op","name":"aten::clone","pid":7,"tid":395,"ts":1677893021977668,"dur":21},{"ph":"X","cat":"cpu_op","name":"aten::empty_like","pid":7,"tid":395,"ts":1677893021977670,"dur":5},{"ph":"X","cat":"cpu_op","name":"aten::empty","pid":7,"tid":395,"ts":1677893021977670,"dur":4},{"ph":"X","cat":"cpu_op","name":"aten::copy_","pid":7,"tid":395,"ts":1677893021977675,"dur":14},{"ph":"X","cat":"cuda_runtime","name":"cudaLaunchKernel","pid":7,"tid":395,"ts":1677893021977680,"dur":6},{"ph":"X","cat":"cpu_op","name":"aten::_unsafe_view","pid":7,"tid":395,"ts":1677893021977710,"dur":2},{"ph":"X","cat":"cpu_op","name":"autograd::engine::evaluate_function: MmBackward0","pid":7,"tid":395,"ts":1677893021977721,"dur":92},{"ph":"X","cat":"cpu_op","name":"MmBackward0","pid":7,"tid":395,"ts":1677893021977723,"dur":82},{"ph":"X","cat":"cpu_op","name":"aten::t","pid":7,"tid":395,"ts":1677893021977726,"dur":3},{"ph":"X","cat":"cpu_op","name":"aten::transpose","pid":7,"tid":395,"ts":1677893021977727,"dur":2},{"ph":"X","cat":"cpu_op","name":"aten::as_strided","pid":7,"tid":395,"ts":1677893021977728,"dur":0},{"ph":"X","cat":"cpu_op","name":"aten::mm","pid":7,"tid":395,"ts":1677893021977730,"dur":42},{"ph":"X","cat":"cuda_runtime","name":"cudaOccupancyMaxActiveBlocksPerMultiprocessorWithFlags","pid":7,"tid":395,"ts":1677893021977747,"dur":1},{"ph":"X","cat":"cuda_runtime","name":"cudaStreamGetCaptureInfo","pid":7,"tid":395,"ts":1677893021977749,"dur":0},{"ph":"X","cat":"cuda_runtime","name":"cudaEventQuery","pid":7,"tid":395,"ts":1677893021977750,"dur":1},{"ph":"X","cat":"cuda_runtime","name":"cudaOccupancyMaxActiveBlocksPerMultiprocessorWithFlags","pid":7,"tid":395,"ts":1677893021977753,"dur":0},{"ph":"X","cat":"cuda_runtime","name":"cudaMemsetAsync","pid":7,"tid":395,"ts":1677893021977754,"dur":5},{"ph":"X","cat":"cuda_runtime","name":"cudaLaunchKernel","pid":7,"tid":395,"ts":1677893021977760,"dur":6},{"ph":"X","cat":"cuda_runtime","name":"cudaStreamGetCaptureInfo","pid":7,"tid":395,"ts":1677893021977768,"dur":0},{"ph":"X","cat":"cuda_runtime","name":"cudaStreamGetCaptureInfo","pid":7,"tid":395,"ts":1677893021977769,"dur":0},{"ph":"X","cat":"cpu_op","name":"aten::t","pid":7,"tid":395,"ts":1677893021977774,"dur":3},{"ph":"X","cat":"cpu_op","name":"aten::transpose","pid":7,"tid":395,"ts":1677893021977775,"dur":2},{"ph":"X","cat":"cpu_op","name":"aten::as_strided","pid":7,"tid":395,"ts":1677893021977776,"dur":0},{"ph":"X","cat":"cpu_op","name":"aten::t","pid":7,"tid":395,"ts":1677893021977779,"dur":2},{"ph":"X","cat":"cpu_op","name":"aten::transpose","pid":7,"tid":395,"ts":1677893021977780,"dur":1},{"ph":"X","cat":"cpu_op","name":"aten::as_strided","pid":7,"tid":395,"ts":1677893021977780,"dur":1},{"ph":"X","cat":"cpu_op","name":"aten::mm","pid":7,"tid":395,"ts":1677893021977782,"dur":22},{"ph":"X","cat":"cuda_runtime","name":"cudaOccupancyMaxActiveBlocksPerMultiprocessorWithFlags","pid":7,"tid":395,"ts":1677893021977795,"dur":0},{"ph":"X","cat":"cuda_runtime","name":"cudaLaunchKernel","pid":7,"tid":395,"ts":1677893021977797,"dur":5},{"ph":"X","cat":"kernel","name":"void at::native::elementwise_kernel<128, 2, at::native::gpu_kernel_impl<at::native::direct_copy_kernel_cuda(at::TensorIteratorBase&)::{lambda()#2}::operator()() const::{lambda()#14}::operator()() const::{lambda(float)#1}>(at::TensorIteratorBase&, at::native::direct_copy_kernel_cuda(at::TensorIteratorBase&)::{lambda()#2}::operator()() const::{lambda()#14}::operator()() const::{lambda(float)#1} const&)::{lambda(int)#1}>(int, at::native::gpu_kernel_impl<at::native::direct_copy_kernel_cuda(at::TensorIteratorBase&)::{lambda()#2}::operator()() const::{lambda()#14}::operator()() const::{lambda(float)#1}>(at::TensorIteratorBase&, at::native::direct_copy_kernel_cuda(at::TensorIteratorBase&)::{lambda()#2}::operator()() const::{lambda()#14}::operator()() const::{lambda(float)#1} const&)::{lambda(int)#1})","pid":0,"tid":7,"ts":1677893022241933,"dur":83},{"ph":"X","cat":"gpu_memset","name":"Memset (Device)","pid":0,"tid":7,"ts":1677893022242017,"dur":1},{"ph":"X","cat":"kernel","name":"void cutlass::Kernel<cutlass_80_simt_sgemm_128x64_8x5_nt_align1>(cutlass_80_simt_sgemm_128x64_8x5_nt_align1::Params)","pid":0,"tid":7,"ts":1677893022242020,"dur":799},{"ph":"X","cat":"kernel","name":"ampere_sgemm_128x64_nn","pid":0,"tid":7,"ts":1677893022242821,"dur":823}]