[{"ph":"X","cat":"cpu_op","name":"aten::zeros","pid":7,"tid":7,"ts":1677890433547555,"dur":4},{"ph":"X","cat":"cpu_op","name":"aten::empty","pid":7,"tid":7,"ts":1677890433547556,"dur":2},{"ph":"X","cat":"cpu_op","name":"aten::zero_","pid":7,"tid":7,"ts":1677890433547558,"dur":1},{"ph":"X","cat":"cpu_op","name":"aten::empty","pid":7,"tid":7,"ts":1677890433547565,"dur":1},{"ph":"X","cat":"cpu_op","name":"aten::conv2d","pid":7,"tid":7,"ts":1677890433547577,"dur":135},{"ph":"X","cat":"cpu_op","name":"aten::convolution","pid":7,"tid":7,"ts":1677890433547578,"dur":134},{"ph":"X","cat":"cpu_op","name":"aten::_convolution","pid":7,"tid":7,"ts":1677890433547583,"dur":127},{"ph":"X","cat":"cpu_op","name":"aten::cudnn_convolution","pid":7,"tid":7,"ts":1677890433547586,"dur":123},{"ph":"X","cat":"cuda_runtime","name":"cudaStreamIsCapturing","pid":7,"tid":7,"ts":1677890433547599,"dur":0},{"ph":"X","cat":"cuda_runtime","name":"cudaStreamGetPriority","pid":7,"tid":7,"ts":1677890433547600,"dur":0},{"ph":"X","cat":"cuda_runtime","name":"cudaDeviceGetStreamPriorityRange","pid":7,"tid":7,"ts":1677890433547601,"dur":0},{"ph":"X","cat":"cpu_op","name":"aten::empty","pid":7,"tid":7,"ts":1677890433547606,"dur":5},{"ph":"X","cat":"cuda_runtime","name":"cudaFuncGetAttributes","pid":7,"tid":7,"ts":1677890433547651,"dur":3},{"ph":"X","cat":"cuda_runtime","name":"cudaFuncGetAttributes","pid":7,"tid":7,"ts":1677890433547655,"dur":2},{"ph":"X","cat":"cuda_runtime","name":"cudaFuncSetAttribute","pid":7,"tid":7,"ts":1677890433547659,"dur":0},{"ph":"X","cat":"cuda_runtime","name":"cudaLaunchKernel","pid":7,"tid":7,"ts":1677890433547668,"dur":10},{"ph":"X","cat":"cuda_runtime","name":"cudaLaunchKernel","pid":7,"tid":7,"ts":1677890433547681,"dur":4},{"ph":"X","cat":"cuda_runtime","name":"cudaFuncSetAttribute","pid":7,"tid":7,"ts":1677890433547687,"dur":0},{"ph":"X","cat":"cuda_runtime","name":"cudaLaunchKernel","pid":7,"tid":7,"ts":1677890433547689,"dur":4},{"ph":"X","cat":"cuda_runtime","name":"cudaLaunchKernel","pid":7,"tid":7,"ts":1677890433547697,"dur":4},{"ph":"X","cat":"kernel","name":"void cudnn::ops::nchwToNhwcKernel<float, float, float, false, true, (cudnnKernelDataType_t)2>(cudnn::ops::nchw2nhwc_params_t<float>, float const*, float*)","pid":0,"tid":7,"ts":1677890433547680,"dur":3},{"ph":"X","cat":"kernel","name":"void cudnn::ops::nchwToNhwcKernel<float, float, float, false, true, (cudnnKernelDataType_t)2>(cudnn::ops::nchw2nhwc_params_t<float>, float const*, float*)","pid":0,"tid":7,"ts":1677890433547688,"dur":26},{"ph":"X","cat":"kernel","name":"void cutlass_cudnn::Kernel<cutlass_tensorop_s1688fprop_optimized_tf32_64x128_16x6_nhwc>(cutlass_tensorop_s1688fprop_optimized_tf32_64x128_16x6_nhwc::Params)","pid":0,"tid":7,"ts":1677890433547715,"dur":157},{"ph":"X","cat":"kernel","name":"void cudnn::ops::nhwcToNchwKernel<float, float, float, true, false, (cudnnKernelDataType_t)0>(cudnn::ops::nhwc2nchw_params_t<float>, float const*, float*)","pid":0,"tid":7,"ts":1677890433547874,"dur":4}]