[{"ph":"X","cat":"cpu_op","name":"aten::zeros","pid":7,"tid":7,"ts":1678128392602100,"dur":4},{"ph":"X","cat":"cpu_op","name":"aten::empty","pid":7,"tid":7,"ts":1678128392602101,"dur":1},{"ph":"X","cat":"cpu_op","name":"aten::zero_","pid":7,"tid":7,"ts":1678128392602103,"dur":0},{"ph":"X","cat":"cpu_op","name":"aten::empty","pid":7,"tid":7,"ts":1678128392602110,"dur":1},{"ph":"X","cat":"cpu_op","name":"aten::conv2d","pid":7,"tid":7,"ts":1678128392602124,"dur":114},{"ph":"X","cat":"cpu_op","name":"aten::convolution","pid":7,"tid":7,"ts":1678128392602125,"dur":113},{"ph":"X","cat":"cpu_op","name":"aten::_convolution","pid":7,"tid":7,"ts":1678128392602131,"dur":104},{"ph":"X","cat":"cpu_op","name":"aten::cudnn_convolution","pid":7,"tid":7,"ts":1678128392602134,"dur":100},{"ph":"X","cat":"cuda_runtime","name":"cudaStreamIsCapturing","pid":7,"tid":7,"ts":1678128392602149,"dur":0},{"ph":"X","cat":"cuda_runtime","name":"cudaStreamGetPriority","pid":7,"tid":7,"ts":1678128392602149,"dur":0},{"ph":"X","cat":"cuda_runtime","name":"cudaDeviceGetStreamPriorityRange","pid":7,"tid":7,"ts":1678128392602150,"dur":0},{"ph":"X","cat":"cpu_op","name":"aten::empty","pid":7,"tid":7,"ts":1678128392602156,"dur":5},{"ph":"X","cat":"cuda_runtime","name":"cudaOccupancyMaxActiveBlocksPerMultiprocessorWithFlags","pid":7,"tid":7,"ts":1678128392602188,"dur":1},{"ph":"X","cat":"cuda_runtime","name":"cudaOccupancyMaxActiveBlocksPerMultiprocessorWithFlags","pid":7,"tid":7,"ts":1678128392602191,"dur":0},{"ph":"X","cat":"cuda_runtime","name":"cudaOccupancyMaxActiveBlocksPerMultiprocessorWithFlags","pid":7,"tid":7,"ts":1678128392602192,"dur":0},{"ph":"X","cat":"cuda_runtime","name":"cudaOccupancyMaxActiveBlocksPerMultiprocessorWithFlags","pid":7,"tid":7,"ts":1678128392602193,"dur":0},{"ph":"X","cat":"cuda_runtime","name":"cudaOccupancyMaxActiveBlocksPerMultiprocessorWithFlags","pid":7,"tid":7,"ts":1678128392602194,"dur":0},{"ph":"X","cat":"cuda_runtime","name":"cudaOccupancyMaxActiveBlocksPerMultiprocessorWithFlags","pid":7,"tid":7,"ts":1678128392602196,"dur":0},{"ph":"X","cat":"cuda_runtime","name":"cudaOccupancyMaxActiveBlocksPerMultiprocessorWithFlags","pid":7,"tid":7,"ts":1678128392602197,"dur":0},{"ph":"X","cat":"cuda_runtime","name":"cudaOccupancyMaxActiveBlocksPerMultiprocessorWithFlags","pid":7,"tid":7,"ts":1678128392602198,"dur":0},{"ph":"X","cat":"cuda_runtime","name":"cudaOccupancyMaxActiveBlocksPerMultiprocessorWithFlags","pid":7,"tid":7,"ts":1678128392602199,"dur":0},{"ph":"X","cat":"cuda_runtime","name":"cudaOccupancyMaxActiveBlocksPerMultiprocessorWithFlags","pid":7,"tid":7,"ts":1678128392602200,"dur":0},{"ph":"X","cat":"cuda_runtime","name":"cudaOccupancyMaxActiveBlocksPerMultiprocessorWithFlags","pid":7,"tid":7,"ts":1678128392602201,"dur":0},{"ph":"X","cat":"cuda_runtime","name":"cudaOccupancyMaxActiveBlocksPerMultiprocessorWithFlags","pid":7,"tid":7,"ts":1678128392602203,"dur":0},{"ph":"X","cat":"cuda_runtime","name":"cudaOccupancyMaxActiveBlocksPerMultiprocessorWithFlags","pid":7,"tid":7,"ts":1678128392602204,"dur":0},{"ph":"X","cat":"cuda_runtime","name":"cudaOccupancyMaxActiveBlocksPerMultiprocessorWithFlags","pid":7,"tid":7,"ts":1678128392602205,"dur":0},{"ph":"X","cat":"cuda_runtime","name":"cudaOccupancyMaxActiveBlocksPerMultiprocessorWithFlags","pid":7,"tid":7,"ts":1678128392602206,"dur":0},{"ph":"X","cat":"cuda_runtime","name":"cudaOccupancyMaxActiveBlocksPerMultiprocessorWithFlags","pid":7,"tid":7,"ts":1678128392602207,"dur":0},{"ph":"X","cat":"cuda_runtime","name":"cudaOccupancyMaxActiveBlocksPerMultiprocessorWithFlags","pid":7,"tid":7,"ts":1678128392602208,"dur":0},{"ph":"X","cat":"cuda_runtime","name":"cudaOccupancyMaxActiveBlocksPerMultiprocessorWithFlags","pid":7,"tid":7,"ts":1678128392602210,"dur":0},{"ph":"X","cat":"cuda_runtime","name":"cudaOccupancyMaxActiveBlocksPerMultiprocessorWithFlags","pid":7,"tid":7,"ts":1678128392602211,"dur":0},{"ph":"X","cat":"cuda_runtime","name":"cudaOccupancyMaxActiveBlocksPerMultiprocessorWithFlags","pid":7,"tid":7,"ts":1678128392602212,"dur":0},{"ph":"X","cat":"cuda_runtime","name":"cudaOccupancyMaxActiveBlocksPerMultiprocessorWithFlags","pid":7,"tid":7,"ts":1678128392602213,"dur":0},{"ph":"X","cat":"cuda_runtime","name":"cudaFuncSetAttribute","pid":7,"tid":7,"ts":1678128392602214,"dur":1},{"ph":"X","cat":"cuda_runtime","name":"cudaLaunchKernel","pid":7,"tid":7,"ts":1678128392602216,"dur":11},{"ph":"X","cat":"kernel","name":"void cutlass::Kernel<cutlass_80_tensorop_s1688gemm_256x64_16x4_nn_align4>(cutlass_80_tensorop_s1688gemm_256x64_16x4_nn_align4::Params)","pid":0,"tid":7,"ts":1678128392602227,"dur":93}]