[{"ph":"X","cat":"cpu_op","name":"aten::zeros","pid":18,"tid":18,"ts":1677894804473686,"dur":5},{"ph":"X","cat":"cpu_op","name":"aten::empty","pid":18,"tid":18,"ts":1677894804473687,"dur":2},{"ph":"X","cat":"cpu_op","name":"aten::zero_","pid":18,"tid":18,"ts":1677894804473690,"dur":1},{"ph":"X","cat":"cpu_op","name":"aten::empty","pid":18,"tid":18,"ts":1677894804473697,"dur":1},{"ph":"X","cat":"cpu_op","name":"aten::matmul","pid":18,"tid":18,"ts":1677894804473702,"dur":60},{"ph":"X","cat":"cpu_op","name":"aten::expand","pid":18,"tid":18,"ts":1677894804473704,"dur":4},{"ph":"X","cat":"cpu_op","name":"aten::as_strided","pid":18,"tid":18,"ts":1677894804473706,"dur":1},{"ph":"X","cat":"cpu_op","name":"aten::reshape","pid":18,"tid":18,"ts":1677894804473709,"dur":5},{"ph":"X","cat":"cpu_op","name":"aten::_reshape_alias","pid":18,"tid":18,"ts":1677894804473712,"dur":2},{"ph":"X","cat":"cpu_op","name":"aten::expand","pid":18,"tid":18,"ts":1677894804473715,"dur":2},{"ph":"X","cat":"cpu_op","name":"aten::as_strided","pid":18,"tid":18,"ts":1677894804473716,"dur":1},{"ph":"X","cat":"cpu_op","name":"aten::reshape","pid":18,"tid":18,"ts":1677894804473718,"dur":3},{"ph":"X","cat":"cpu_op","name":"aten::_reshape_alias","pid":18,"tid":18,"ts":1677894804473719,"dur":1},{"ph":"X","cat":"cpu_op","name":"aten::bmm","pid":18,"tid":18,"ts":1677894804473722,"dur":36},{"ph":"X","cat":"cuda_runtime","name":"cudaOccupancyMaxActiveBlocksPerMultiprocessorWithFlags","pid":18,"tid":18,"ts":1677894804473739,"dur":1},{"ph":"X","cat":"cuda_runtime","name":"cudaOccupancyMaxActiveBlocksPerMultiprocessorWithFlags","pid":18,"tid":18,"ts":1677894804473740,"dur":0},{"ph":"X","cat":"cuda_runtime","name":"cudaOccupancyMaxActiveBlocksPerMultiprocessorWithFlags","pid":18,"tid":18,"ts":1677894804473741,"dur":0},{"ph":"X","cat":"cuda_runtime","name":"cudaOccupancyMaxActiveBlocksPerMultiprocessorWithFlags","pid":18,"tid":18,"ts":1677894804473742,"dur":0},{"ph":"X","cat":"cuda_runtime","name":"cudaOccupancyMaxActiveBlocksPerMultiprocessorWithFlags","pid":18,"tid":18,"ts":1677894804473743,"dur":0},{"ph":"X","cat":"cuda_runtime","name":"cudaOccupancyMaxActiveBlocksPerMultiprocessorWithFlags","pid":18,"tid":18,"ts":1677894804473744,"dur":0},{"ph":"X","cat":"cuda_runtime","name":"cudaLaunchKernel","pid":18,"tid":18,"ts":1677894804473746,"dur":9},{"ph":"X","cat":"cpu_op","name":"aten::_unsafe_view","pid":18,"tid":18,"ts":1677894804473760,"dur":1},{"ph":"X","cat":"kernel","name":"ampere_sgemm_128x128_nn","pid":0,"tid":7,"ts":1677894804473757,"dur":15}]