[{"ph":"X","cat":"cpu_op","name":"aten::zeros","pid":18,"tid":18,"ts":1678058561964787,"dur":4},{"ph":"X","cat":"cpu_op","name":"aten::empty","pid":18,"tid":18,"ts":1678058561964788,"dur":2},{"ph":"X","cat":"cpu_op","name":"aten::zero_","pid":18,"tid":18,"ts":1678058561964791,"dur":0},{"ph":"X","cat":"cpu_op","name":"aten::empty","pid":18,"tid":18,"ts":1678058561964797,"dur":1},{"ph":"X","cat":"cpu_op","name":"aten::zeros","pid":18,"tid":18,"ts":1678058561964873,"dur":3},{"ph":"X","cat":"cpu_op","name":"aten::empty","pid":18,"tid":18,"ts":1678058561964874,"dur":1},{"ph":"X","cat":"cpu_op","name":"aten::zero_","pid":18,"tid":18,"ts":1678058561964876,"dur":0},{"ph":"X","cat":"cpu_op","name":"aten::empty","pid":18,"tid":18,"ts":1678058561964882,"dur":1},{"ph":"X","cat":"cpu_op","name":"aten::linear","pid":18,"tid":18,"ts":1678058561964891,"dur":68},{"ph":"X","cat":"cpu_op","name":"aten::t","pid":18,"tid":18,"ts":1678058561964892,"dur":6},{"ph":"X","cat":"cpu_op","name":"aten::transpose","pid":18,"tid":18,"ts":1678058561964894,"dur":3},{"ph":"X","cat":"cpu_op","name":"aten::as_strided","pid":18,"tid":18,"ts":1678058561964895,"dur":1},{"ph":"X","cat":"cpu_op","name":"aten::view","pid":18,"tid":18,"ts":1678058561964899,"dur":1},{"ph":"X","cat":"cpu_op","name":"aten::addmm","pid":18,"tid":18,"ts":1678058561964901,"dur":54},{"ph":"X","cat":"cpu_op","name":"aten::empty","pid":18,"tid":18,"ts":1678058561964914,"dur":4},{"ph":"X","cat":"cuda_runtime","name":"cudaOccupancyMaxActiveBlocksPerMultiprocessorWithFlags","pid":18,"tid":18,"ts":1678058561964928,"dur":1},{"ph":"X","cat":"cuda_runtime","name":"cudaMemsetAsync","pid":18,"tid":18,"ts":1678058561964932,"dur":6},{"ph":"X","cat":"cuda_runtime","name":"cudaOccupancyMaxActiveBlocksPerMultiprocessorWithFlags","pid":18,"tid":18,"ts":1678058561964940,"dur":0},{"ph":"X","cat":"cuda_runtime","name":"cudaLaunchKernel","pid":18,"tid":18,"ts":1678058561964941,"dur":9},{"ph":"X","cat":"cpu_op","name":"aten::view","pid":18,"tid":18,"ts":1678058561964957,"dur":2},{"ph":"X","cat":"cpu_op","name":"aten::chunk","pid":18,"tid":18,"ts":1678058561964964,"dur":16},{"ph":"X","cat":"cpu_op","name":"aten::split","pid":18,"tid":18,"ts":1678058561964967,"dur":13},{"ph":"X","cat":"cpu_op","name":"aten::narrow","pid":18,"tid":18,"ts":1678058561964969,"dur":4},{"ph":"X","cat":"cpu_op","name":"aten::slice","pid":18,"tid":18,"ts":1678058561964970,"dur":3},{"ph":"X","cat":"cpu_op","name":"aten::as_strided","pid":18,"tid":18,"ts":1678058561964971,"dur":1},{"ph":"X","cat":"cpu_op","name":"aten::narrow","pid":18,"tid":18,"ts":1678058561964974,"dur":2},{"ph":"X","cat":"cpu_op","name":"aten::slice","pid":18,"tid":18,"ts":1678058561964975,"dur":1},{"ph":"X","cat":"cpu_op","name":"aten::as_strided","pid":18,"tid":18,"ts":1678058561964975,"dur":1},{"ph":"X","cat":"cpu_op","name":"aten::narrow","pid":18,"tid":18,"ts":1678058561964977,"dur":2},{"ph":"X","cat":"cpu_op","name":"aten::slice","pid":18,"tid":18,"ts":1678058561964977,"dur":2},{"ph":"X","cat":"cpu_op","name":"aten::as_strided","pid":18,"tid":18,"ts":1678058561964978,"dur":1},{"ph":"X","cat":"cpu_op","name":"aten::zeros","pid":18,"tid":18,"ts":1678058561965068,"dur":5},{"ph":"X","cat":"cpu_op","name":"aten::empty","pid":18,"tid":18,"ts":1678058561965069,"dur":2},{"ph":"X","cat":"cpu_op","name":"aten::zero_","pid":18,"tid":18,"ts":1678058561965072,"dur":1},{"ph":"X","cat":"cpu_op","name":"aten::empty","pid":18,"tid":18,"ts":1678058561965079,"dur":1},{"ph":"X","cat":"cpu_op","name":"aten::view","pid":18,"tid":18,"ts":1678058561965085,"dur":3},{"ph":"X","cat":"cpu_op","name":"aten::transpose","pid":18,"tid":18,"ts":1678058561965090,"dur":3},{"ph":"X","cat":"cpu_op","name":"aten::as_strided","pid":18,"tid":18,"ts":1678058561965091,"dur":1},{"ph":"X","cat":"cpu_op","name":"aten::view","pid":18,"tid":18,"ts":1678058561965096,"dur":1},{"ph":"X","cat":"cpu_op","name":"aten::transpose","pid":18,"tid":18,"ts":1678058561965099,"dur":2},{"ph":"X","cat":"cpu_op","name":"aten::as_strided","pid":18,"tid":18,"ts":1678058561965099,"dur":1},{"ph":"X","cat":"cpu_op","name":"aten::view","pid":18,"tid":18,"ts":1678058561965103,"dur":1},{"ph":"X","cat":"cpu_op","name":"aten::transpose","pid":18,"tid":18,"ts":1678058561965106,"dur":2},{"ph":"X","cat":"cpu_op","name":"aten::as_strided","pid":18,"tid":18,"ts":1678058561965107,"dur":0},{"ph":"X","cat":"cpu_op","name":"aten::transpose","pid":18,"tid":18,"ts":1678058561965110,"dur":2},{"ph":"X","cat":"cpu_op","name":"aten::as_strided","pid":18,"tid":18,"ts":1678058561965111,"dur":0},{"ph":"X","cat":"cpu_op","name":"aten::matmul","pid":18,"tid":18,"ts":1678058561965114,"dur":61},{"ph":"X","cat":"cpu_op","name":"aten::expand","pid":18,"tid":18,"ts":1678058561965116,"dur":3},{"ph":"X","cat":"cpu_op","name":"aten::as_strided","pid":18,"tid":18,"ts":1678058561965117,"dur":1},{"ph":"X","cat":"cpu_op","name":"aten::reshape","pid":18,"tid":18,"ts":1678058561965120,"dur":4},{"ph":"X","cat":"cpu_op","name":"aten::_reshape_alias","pid":18,"tid":18,"ts":1678058561965122,"dur":2},{"ph":"X","cat":"cpu_op","name":"aten::expand","pid":18,"tid":18,"ts":1678058561965125,"dur":2},{"ph":"X","cat":"cpu_op","name":"aten::as_strided","pid":18,"tid":18,"ts":1678058561965126,"dur":1},{"ph":"X","cat":"cpu_op","name":"aten::reshape","pid":18,"tid":18,"ts":1678058561965128,"dur":2},{"ph":"X","cat":"cpu_op","name":"aten::_reshape_alias","pid":18,"tid":18,"ts":1678058561965129,"dur":1},{"ph":"X","cat":"cpu_op","name":"aten::bmm","pid":18,"tid":18,"ts":1678058561965131,"dur":40},{"ph":"X","cat":"cuda_runtime","name":"cudaOccupancyMaxActiveBlocksPerMultiprocessorWithFlags","pid":18,"tid":18,"ts":1678058561965150,"dur":1},{"ph":"X","cat":"cuda_runtime","name":"cudaOccupancyMaxActiveBlocksPerMultiprocessorWithFlags","pid":18,"tid":18,"ts":1678058561965152,"dur":0},{"ph":"X","cat":"cuda_runtime","name":"cudaOccupancyMaxActiveBlocksPerMultiprocessorWithFlags","pid":18,"tid":18,"ts":1678058561965153,"dur":0},{"ph":"X","cat":"cuda_runtime","name":"cudaOccupancyMaxActiveBlocksPerMultiprocessorWithFlags","pid":18,"tid":18,"ts":1678058561965153,"dur":0},{"ph":"X","cat":"cuda_runtime","name":"cudaOccupancyMaxActiveBlocksPerMultiprocessorWithFlags","pid":18,"tid":18,"ts":1678058561965154,"dur":0},{"ph":"X","cat":"cuda_runtime","name":"cudaOccupancyMaxActiveBlocksPerMultiprocessorWithFlags","pid":18,"tid":18,"ts":1678058561965155,"dur":0},{"ph":"X","cat":"cuda_runtime","name":"cudaLaunchKernel","pid":18,"tid":18,"ts":1678058561965158,"dur":10},{"ph":"X","cat":"cpu_op","name":"aten::_unsafe_view","pid":18,"tid":18,"ts":1678058561965172,"dur":2},{"ph":"X","cat":"cpu_op","name":"aten::zeros","pid":18,"tid":18,"ts":1678058561965259,"dur":4},{"ph":"X","cat":"cpu_op","name":"aten::empty","pid":18,"tid":18,"ts":1678058561965260,"dur":1},{"ph":"X","cat":"cpu_op","name":"aten::zero_","pid":18,"tid":18,"ts":1678058561965263,"dur":0},{"ph":"X","cat":"cpu_op","name":"aten::empty","pid":18,"tid":18,"ts":1678058561965269,"dur":1},{"ph":"X","cat":"cpu_op","name":"aten::ones_like","pid":18,"tid":18,"ts":1678058561965275,"dur":29},{"ph":"X","cat":"cpu_op","name":"aten::empty_like","pid":18,"tid":18,"ts":1678058561965276,"dur":9},{"ph":"X","cat":"cpu_op","name":"aten::empty_strided","pid":18,"tid":18,"ts":1678058561965277,"dur":7},{"ph":"X","cat":"cpu_op","name":"aten::fill_","pid":18,"tid":18,"ts":1678058561965286,"dur":17},{"ph":"X","cat":"cuda_runtime","name":"cudaLaunchKernel","pid":18,"tid":18,"ts":1678058561965292,"dur":10},{"ph":"X","cat":"cpu_op","name":"aten::triu","pid":18,"tid":18,"ts":1678058561965307,"dur":15},{"ph":"X","cat":"cuda_runtime","name":"cudaLaunchKernel","pid":18,"tid":18,"ts":1678058561965314,"dur":5},{"ph":"X","cat":"cpu_op","name":"aten::masked_fill_","pid":18,"tid":18,"ts":1678058561965327,"dur":13},{"ph":"X","cat":"cuda_runtime","name":"cudaLaunchKernel","pid":18,"tid":18,"ts":1678058561965332,"dur":6},{"ph":"X","cat":"cpu_op","name":"aten::div_","pid":18,"tid":18,"ts":1678058561965345,"dur":15},{"ph":"X","cat":"cuda_runtime","name":"cudaLaunchKernel","pid":18,"tid":18,"ts":1678058561965353,"dur":5},{"ph":"X","cat":"cpu_op","name":"aten::softmax","pid":18,"tid":18,"ts":1678058561965364,"dur":18},{"ph":"X","cat":"cpu_op","name":"aten::_softmax","pid":18,"tid":18,"ts":1678058561965365,"dur":16},{"ph":"X","cat":"cuda_runtime","name":"cudaLaunchKernel","pid":18,"tid":18,"ts":1678058561965374,"dur":5},{"ph":"X","cat":"cpu_op","name":"aten::zeros","pid":18,"tid":18,"ts":1678058561965465,"dur":5},{"ph":"X","cat":"cpu_op","name":"aten::empty","pid":18,"tid":18,"ts":1678058561965466,"dur":2},{"ph":"X","cat":"cpu_op","name":"aten::zero_","pid":18,"tid":18,"ts":1678058561965469,"dur":0},{"ph":"X","cat":"cpu_op","name":"aten::empty","pid":18,"tid":18,"ts":1678058561965476,"dur":1},{"ph":"X","cat":"cpu_op","name":"aten::matmul","pid":18,"tid":18,"ts":1678058561965481,"dur":60},{"ph":"X","cat":"cpu_op","name":"aten::expand","pid":18,"tid":18,"ts":1678058561965482,"dur":5},{"ph":"X","cat":"cpu_op","name":"aten::as_strided","pid":18,"tid":18,"ts":1678058561965484,"dur":2},{"ph":"X","cat":"cpu_op","name":"aten::reshape","pid":18,"tid":18,"ts":1678058561965488,"dur":5},{"ph":"X","cat":"cpu_op","name":"aten::_reshape_alias","pid":18,"tid":18,"ts":1678058561965490,"dur":2},{"ph":"X","cat":"cpu_op","name":"aten::expand","pid":18,"tid":18,"ts":1678058561965494,"dur":2},{"ph":"X","cat":"cpu_op","name":"aten::as_strided","pid":18,"tid":18,"ts":1678058561965494,"dur":1},{"ph":"X","cat":"cpu_op","name":"aten::reshape","pid":18,"tid":18,"ts":1678058561965496,"dur":3},{"ph":"X","cat":"cpu_op","name":"aten::_reshape_alias","pid":18,"tid":18,"ts":1678058561965498,"dur":1},{"ph":"X","cat":"cpu_op","name":"aten::bmm","pid":18,"tid":18,"ts":1678058561965500,"dur":37},{"ph":"X","cat":"cuda_runtime","name":"cudaOccupancyMaxActiveBlocksPerMultiprocessorWithFlags","pid":18,"tid":18,"ts":1678058561965517,"dur":1},{"ph":"X","cat":"cuda_runtime","name":"cudaOccupancyMaxActiveBlocksPerMultiprocessorWithFlags","pid":18,"tid":18,"ts":1678058561965519,"dur":0},{"ph":"X","cat":"cuda_runtime","name":"cudaOccupancyMaxActiveBlocksPerMultiprocessorWithFlags","pid":18,"tid":18,"ts":1678058561965520,"dur":0},{"ph":"X","cat":"cuda_runtime","name":"cudaOccupancyMaxActiveBlocksPerMultiprocessorWithFlags","pid":18,"tid":18,"ts":1678058561965521,"dur":0},{"ph":"X","cat":"cuda_runtime","name":"cudaOccupancyMaxActiveBlocksPerMultiprocessorWithFlags","pid":18,"tid":18,"ts":1678058561965521,"dur":0},{"ph":"X","cat":"cuda_runtime","name":"cudaOccupancyMaxActiveBlocksPerMultiprocessorWithFlags","pid":18,"tid":18,"ts":1678058561965522,"dur":0},{"ph":"X","cat":"cuda_runtime","name":"cudaLaunchKernel","pid":18,"tid":18,"ts":1678058561965525,"dur":10},{"ph":"X","cat":"cpu_op","name":"aten::_unsafe_view","pid":18,"tid":18,"ts":1678058561965539,"dur":1},{"ph":"X","cat":"cpu_op","name":"aten::zeros","pid":18,"tid":18,"ts":1678058561965621,"dur":4},{"ph":"X","cat":"cpu_op","name":"aten::empty","pid":18,"tid":18,"ts":1678058561965622,"dur":1},{"ph":"X","cat":"cpu_op","name":"aten::zero_","pid":18,"tid":18,"ts":1678058561965624,"dur":1},{"ph":"X","cat":"cpu_op","name":"aten::empty","pid":18,"tid":18,"ts":1678058561965631,"dur":1},{"ph":"X","cat":"cpu_op","name":"aten::transpose","pid":18,"tid":18,"ts":1678058561965636,"dur":4},{"ph":"X","cat":"cpu_op","name":"aten::as_strided","pid":18,"tid":18,"ts":1678058561965637,"dur":2},{"ph":"X","cat":"cpu_op","name":"aten::reshape","pid":18,"tid":18,"ts":1678058561965642,"dur":38},{"ph":"X","cat":"cpu_op","name":"aten::clone","pid":18,"tid":18,"ts":1678058561965644,"dur":33},{"ph":"X","cat":"cpu_op","name":"aten::empty_like","pid":18,"tid":18,"ts":1678058561965646,"dur":9},{"ph":"X","cat":"cpu_op","name":"aten::empty","pid":18,"tid":18,"ts":1678058561965647,"dur":7},{"ph":"X","cat":"cpu_op","name":"aten::copy_","pid":18,"tid":18,"ts":1678058561965656,"dur":21},{"ph":"X","cat":"cuda_runtime","name":"cudaLaunchKernel","pid":18,"tid":18,"ts":1678058561965664,"dur":10},{"ph":"X","cat":"cpu_op","name":"aten::_unsafe_view","pid":18,"tid":18,"ts":1678058561965678,"dur":1},{"ph":"X","cat":"cpu_op","name":"aten::linear","pid":18,"tid":18,"ts":1678058561965692,"dur":60},{"ph":"X","cat":"cpu_op","name":"aten::t","pid":18,"tid":18,"ts":1678058561965693,"dur":4},{"ph":"X","cat":"cpu_op","name":"aten::transpose","pid":18,"tid":18,"ts":1678058561965694,"dur":2},{"ph":"X","cat":"cpu_op","name":"aten::as_strided","pid":18,"tid":18,"ts":1678058561965695,"dur":1},{"ph":"X","cat":"cpu_op","name":"aten::view","pid":18,"tid":18,"ts":1678058561965698,"dur":1},{"ph":"X","cat":"cpu_op","name":"aten::addmm","pid":18,"tid":18,"ts":1678058561965700,"dur":48},{"ph":"X","cat":"cpu_op","name":"aten::empty","pid":18,"tid":18,"ts":1678058561965710,"dur":5},{"ph":"X","cat":"cuda_runtime","name":"cudaOccupancyMaxActiveBlocksPerMultiprocessorWithFlags","pid":18,"tid":18,"ts":1678058561965725,"dur":1},{"ph":"X","cat":"cuda_runtime","name":"cudaOccupancyMaxActiveBlocksPerMultiprocessorWithFlags","pid":18,"tid":18,"ts":1678058561965729,"dur":0},{"ph":"X","cat":"cuda_runtime","name":"cudaLaunchKernel","pid":18,"tid":18,"ts":1678058561965731,"dur":7},{"ph":"X","cat":"cuda_runtime","name":"cudaLaunchKernel","pid":18,"tid":18,"ts":1678058561965739,"dur":5},{"ph":"X","cat":"cpu_op","name":"aten::view","pid":18,"tid":18,"ts":1678058561965750,"dur":1},{"ph":"X","cat":"gpu_memset","name":"Memset (Device)","pid":0,"tid":7,"ts":1678058561964942,"dur":1},{"ph":"X","cat":"kernel","name":"ampere_sgemm_128x32_tn","pid":0,"tid":7,"ts":1678058561964952,"dur":32},{"ph":"X","cat":"kernel","name":"ampere_sgemm_128x128_tn","pid":0,"tid":7,"ts":1678058561965170,"dur":14},{"ph":"X","cat":"kernel","name":"void at::native::vectorized_elementwise_kernel<4, at::native::FillFunctor<bool>, at::detail::Array<char*, 1> >(int, at::native::FillFunctor<bool>, at::detail::Array<char*, 1>)","pid":0,"tid":7,"ts":1678058561965302,"dur":2},{"ph":"X","cat":"kernel","name":"void at::native::triu_tril_kernel<bool, int, true>(at::cuda::detail::TensorInfo<bool, int>, at::cuda::detail::TensorInfo<bool, int>, long, long)","pid":0,"tid":7,"ts":1678058561965322,"dur":4},{"ph":"X","cat":"kernel","name":"void at::native::vectorized_elementwise_kernel<4, at::native::(anonymous namespace)::masked_fill_kernel<bool>(at::TensorIterator&, c10::Scalar const&)::{lambda()#1}::operator()() const::{lambda()#14}::operator()() const::{lambda(float, bool)#1}, at::detail::Array<char*, 3> >(int, at::native::(anonymous namespace)::masked_fill_kernel<bool>(at::TensorIterator&, c10::Scalar const&)::{lambda()#1}::operator()() const::{lambda()#14}::operator()() const::{lambda(float, bool)#1}, at::detail::Array<char*, 3>)","pid":0,"tid":7,"ts":1678058561965340,"dur":2},{"ph":"X","cat":"kernel","name":"void at::native::vectorized_elementwise_kernel<4, at::native::BUnaryFunctor<float, float, float, at::native::binary_internal::MulFunctor<float> >, at::detail::Array<char*, 2> >(int, at::native::BUnaryFunctor<float, float, float, at::native::binary_internal::MulFunctor<float> >, at::detail::Array<char*, 2>)","pid":0,"tid":7,"ts":1678058561965360,"dur":2},{"ph":"X","cat":"kernel","name":"void (anonymous namespace)::softmax_warp_forward<float, float, float, 7, false, false>(float*, float const*, int, int, int, bool const*, int, bool)","pid":0,"tid":7,"ts":1678058561965381,"dur":4},{"ph":"X","cat":"kernel","name":"ampere_sgemm_128x128_nn","pid":0,"tid":7,"ts":1678058561965536,"dur":15},{"ph":"X","cat":"kernel","name":"void at::native::elementwise_kernel<128, 2, at::native::gpu_kernel_impl<at::native::direct_copy_kernel_cuda(at::TensorIteratorBase&)::{lambda()#2}::operator()() const::{lambda()#14}::operator()() const::{lambda(float)#1}>(at::TensorIteratorBase&, at::native::direct_copy_kernel_cuda(at::TensorIteratorBase&)::{lambda()#2}::operator()() const::{lambda()#14}::operator()() const::{lambda(float)#1} const&)::{lambda(int)#1}>(int, at::native::gpu_kernel_impl<at::native::direct_copy_kernel_cuda(at::TensorIteratorBase&)::{lambda()#2}::operator()() const::{lambda()#14}::operator()() const::{lambda(float)#1}>(at::TensorIteratorBase&, at::native::direct_copy_kernel_cuda(at::TensorIteratorBase&)::{lambda()#2}::operator()() const::{lambda()#14}::operator()() const::{lambda(float)#1} const&)::{lambda(int)#1})","pid":0,"tid":7,"ts":1678058561965675,"dur":3},{"ph":"X","cat":"kernel","name":"ampere_sgemm_64x32_sliced1x4_tn","pid":0,"tid":7,"ts":1678058561965740,"dur":15},{"ph":"X","cat":"kernel","name":"void splitKreduce_kernel<32, 16, int, float, float, float, float, true, true, false>(cublasSplitKParams<float>, float const*, float const*, float*, float const*, float const*, float const*, float const*, float*, void*, long, float*, int*)","pid":0,"tid":7,"ts":1678058561965756,"dur":3}]