[{"ph":"X","cat":"cpu_op","name":"aten::zeros","pid":18,"tid":18,"ts":1677894810995099,"dur":6},{"ph":"X","cat":"cpu_op","name":"aten::empty","pid":18,"tid":18,"ts":1677894810995100,"dur":3},{"ph":"X","cat":"cpu_op","name":"aten::zero_","pid":18,"tid":18,"ts":1677894810995104,"dur":0},{"ph":"X","cat":"cpu_op","name":"aten::empty","pid":18,"tid":18,"ts":1677894810995112,"dur":1},{"ph":"X","cat":"cpu_op","name":"aten::zeros","pid":18,"tid":18,"ts":1677894810995200,"dur":3},{"ph":"X","cat":"cpu_op","name":"aten::empty","pid":18,"tid":18,"ts":1677894810995200,"dur":2},{"ph":"X","cat":"cpu_op","name":"aten::zero_","pid":18,"tid":18,"ts":1677894810995202,"dur":1},{"ph":"X","cat":"cpu_op","name":"aten::empty","pid":18,"tid":18,"ts":1677894810995209,"dur":1},{"ph":"X","cat":"cpu_op","name":"aten::zeros","pid":18,"tid":18,"ts":1677894810995285,"dur":3},{"ph":"X","cat":"cpu_op","name":"aten::empty","pid":18,"tid":18,"ts":1677894810995286,"dur":1},{"ph":"X","cat":"cpu_op","name":"aten::zero_","pid":18,"tid":18,"ts":1677894810995287,"dur":0},{"ph":"X","cat":"cpu_op","name":"aten::empty","pid":18,"tid":18,"ts":1677894810995292,"dur":1},{"ph":"X","cat":"cpu_op","name":"aten::group_norm","pid":18,"tid":18,"ts":1677894810995311,"dur":101},{"ph":"X","cat":"cpu_op","name":"aten::contiguous","pid":18,"tid":18,"ts":1677894810995312,"dur":35},{"ph":"X","cat":"cpu_op","name":"aten::clone","pid":18,"tid":18,"ts":1677894810995313,"dur":34},{"ph":"X","cat":"cpu_op","name":"aten::empty_like","pid":18,"tid":18,"ts":1677894810995314,"dur":10},{"ph":"X","cat":"cpu_op","name":"aten::empty","pid":18,"tid":18,"ts":1677894810995315,"dur":8},{"ph":"X","cat":"cpu_op","name":"aten::copy_","pid":18,"tid":18,"ts":1677894810995325,"dur":21},{"ph":"X","cat":"cuda_runtime","name":"cudaLaunchKernel","pid":18,"tid":18,"ts":1677894810995332,"dur":11},{"ph":"X","cat":"cpu_op","name":"aten::native_group_norm","pid":18,"tid":18,"ts":1677894810995348,"dur":62},{"ph":"X","cat":"cpu_op","name":"aten::empty","pid":18,"tid":18,"ts":1677894810995352,"dur":4},{"ph":"X","cat":"cpu_op","name":"aten::empty","pid":18,"tid":18,"ts":1677894810995357,"dur":4},{"ph":"X","cat":"cpu_op","name":"aten::empty","pid":18,"tid":18,"ts":1677894810995361,"dur":4},{"ph":"X","cat":"cuda_runtime","name":"cudaLaunchKernel","pid":18,"tid":18,"ts":1677894810995367,"dur":6},{"ph":"X","cat":"cpu_op","name":"aten::empty","pid":18,"tid":18,"ts":1677894810995375,"dur":4},{"ph":"X","cat":"cpu_op","name":"aten::empty","pid":18,"tid":18,"ts":1677894810995380,"dur":3},{"ph":"X","cat":"cuda_runtime","name":"cudaLaunchKernel","pid":18,"tid":18,"ts":1677894810995384,"dur":5},{"ph":"X","cat":"cpu_op","name":"aten::view","pid":18,"tid":18,"ts":1677894810995391,"dur":1},{"ph":"X","cat":"cpu_op","name":"aten::view","pid":18,"tid":18,"ts":1677894810995393,"dur":0},{"ph":"X","cat":"cpu_op","name":"aten::view","pid":18,"tid":18,"ts":1677894810995394,"dur":0},{"ph":"X","cat":"cpu_op","name":"aten::view","pid":18,"tid":18,"ts":1677894810995395,"dur":0},{"ph":"X","cat":"cuda_runtime","name":"cudaLaunchKernel","pid":18,"tid":18,"ts":1677894810995400,"dur":5},{"ph":"X","cat":"cpu_op","name":"aten::zeros","pid":18,"tid":18,"ts":1677894810995499,"dur":4},{"ph":"X","cat":"cpu_op","name":"aten::empty","pid":18,"tid":18,"ts":1677894810995500,"dur":2},{"ph":"X","cat":"cpu_op","name":"aten::zero_","pid":18,"tid":18,"ts":1677894810995503,"dur":0},{"ph":"X","cat":"cpu_op","name":"aten::empty","pid":18,"tid":18,"ts":1677894810995509,"dur":1},{"ph":"X","cat":"cpu_op","name":"aten::silu","pid":18,"tid":18,"ts":1677894810995515,"dur":22},{"ph":"X","cat":"cuda_runtime","name":"cudaLaunchKernel","pid":18,"tid":18,"ts":1677894810995526,"dur":9},{"ph":"X","cat":"cpu_op","name":"aten::zeros","pid":18,"tid":18,"ts":1677894810995617,"dur":4},{"ph":"X","cat":"cpu_op","name":"aten::empty","pid":18,"tid":18,"ts":1677894810995618,"dur":2},{"ph":"X","cat":"cpu_op","name":"aten::zero_","pid":18,"tid":18,"ts":1677894810995621,"dur":0},{"ph":"X","cat":"cpu_op","name":"aten::empty","pid":18,"tid":18,"ts":1677894810995627,"dur":0},{"ph":"X","cat":"cpu_op","name":"aten::conv2d","pid":18,"tid":18,"ts":1677894810995640,"dur":157},{"ph":"X","cat":"cpu_op","name":"aten::convolution","pid":18,"tid":18,"ts":1677894810995641,"dur":155},{"ph":"X","cat":"cpu_op","name":"aten::_convolution","pid":18,"tid":18,"ts":1677894810995643,"dur":153},{"ph":"X","cat":"cpu_op","name":"aten::cudnn_convolution","pid":18,"tid":18,"ts":1677894810995648,"dur":121},{"ph":"X","cat":"cuda_runtime","name":"cudaStreamIsCapturing","pid":18,"tid":18,"ts":1677894810995662,"dur":0},{"ph":"X","cat":"cuda_runtime","name":"cudaStreamGetPriority","pid":18,"tid":18,"ts":1677894810995663,"dur":0},{"ph":"X","cat":"cuda_runtime","name":"cudaDeviceGetStreamPriorityRange","pid":18,"tid":18,"ts":1677894810995663,"dur":0},{"ph":"X","cat":"cpu_op","name":"aten::empty","pid":18,"tid":18,"ts":1677894810995669,"dur":4},{"ph":"X","cat":"cuda_runtime","name":"cudaFuncGetAttributes","pid":18,"tid":18,"ts":1677894810995709,"dur":3},{"ph":"X","cat":"cuda_runtime","name":"cudaFuncSetAttribute","pid":18,"tid":18,"ts":1677894810995714,"dur":0},{"ph":"X","cat":"cuda_runtime","name":"cudaLaunchKernel","pid":18,"tid":18,"ts":1677894810995724,"dur":10},{"ph":"X","cat":"cuda_runtime","name":"cudaLaunchKernel","pid":18,"tid":18,"ts":1677894810995736,"dur":5},{"ph":"X","cat":"cuda_runtime","name":"cudaFuncSetAttribute","pid":18,"tid":18,"ts":1677894810995743,"dur":0},{"ph":"X","cat":"cuda_runtime","name":"cudaLaunchKernel","pid":18,"tid":18,"ts":1677894810995745,"dur":5},{"ph":"X","cat":"cuda_runtime","name":"cudaLaunchKernel","pid":18,"tid":18,"ts":1677894810995752,"dur":4},{"ph":"X","cat":"cpu_op","name":"aten::reshape","pid":18,"tid":18,"ts":1677894810995772,"dur":4},{"ph":"X","cat":"cpu_op","name":"aten::_reshape_alias","pid":18,"tid":18,"ts":1677894810995775,"dur":1},{"ph":"X","cat":"cpu_op","name":"aten::add_","pid":18,"tid":18,"ts":1677894810995777,"dur":18},{"ph":"X","cat":"cuda_runtime","name":"cudaLaunchKernel","pid":18,"tid":18,"ts":1677894810995786,"dur":6},{"ph":"X","cat":"cpu_op","name":"aten::zeros","pid":18,"tid":18,"ts":1677894810995892,"dur":5},{"ph":"X","cat":"cpu_op","name":"aten::empty","pid":18,"tid":18,"ts":1677894810995893,"dur":2},{"ph":"X","cat":"cpu_op","name":"aten::zero_","pid":18,"tid":18,"ts":1677894810995896,"dur":1},{"ph":"X","cat":"cpu_op","name":"aten::empty","pid":18,"tid":18,"ts":1677894810995904,"dur":0},{"ph":"X","cat":"cpu_op","name":"aten::silu","pid":18,"tid":18,"ts":1677894810995909,"dur":23},{"ph":"X","cat":"cuda_runtime","name":"cudaLaunchKernel","pid":18,"tid":18,"ts":1677894810995921,"dur":9},{"ph":"X","cat":"cpu_op","name":"aten::zeros","pid":18,"tid":18,"ts":1677894810996011,"dur":4},{"ph":"X","cat":"cpu_op","name":"aten::empty","pid":18,"tid":18,"ts":1677894810996012,"dur":1},{"ph":"X","cat":"cpu_op","name":"aten::zero_","pid":18,"tid":18,"ts":1677894810996014,"dur":0},{"ph":"X","cat":"cpu_op","name":"aten::empty","pid":18,"tid":18,"ts":1677894810996020,"dur":1},{"ph":"X","cat":"cpu_op","name":"aten::linear","pid":18,"tid":18,"ts":1677894810996031,"dur":61},{"ph":"X","cat":"cpu_op","name":"aten::t","pid":18,"tid":18,"ts":1677894810996031,"dur":6},{"ph":"X","cat":"cpu_op","name":"aten::transpose","pid":18,"tid":18,"ts":1677894810996033,"dur":3},{"ph":"X","cat":"cpu_op","name":"aten::as_strided","pid":18,"tid":18,"ts":1677894810996034,"dur":2},{"ph":"X","cat":"cpu_op","name":"aten::addmm","pid":18,"tid":18,"ts":1677894810996038,"dur":53},{"ph":"X","cat":"cpu_op","name":"aten::empty","pid":18,"tid":18,"ts":1677894810996050,"dur":4},{"ph":"X","cat":"cuda_runtime","name":"cudaOccupancyMaxActiveBlocksPerMultiprocessorWithFlags","pid":18,"tid":18,"ts":1677894810996061,"dur":1},{"ph":"X","cat":"cuda_runtime","name":"cudaLaunchKernel","pid":18,"tid":18,"ts":1677894810996065,"dur":9},{"ph":"X","cat":"cuda_runtime","name":"cudaLaunchKernel","pid":18,"tid":18,"ts":1677894810996076,"dur":5},{"ph":"X","cat":"cuda_runtime","name":"cudaLaunchKernel","pid":18,"tid":18,"ts":1677894810996083,"dur":4},{"ph":"X","cat":"cpu_op","name":"aten::zeros","pid":18,"tid":18,"ts":1677894810996177,"dur":4},{"ph":"X","cat":"cpu_op","name":"aten::empty","pid":18,"tid":18,"ts":1677894810996178,"dur":2},{"ph":"X","cat":"cpu_op","name":"aten::zero_","pid":18,"tid":18,"ts":1677894810996181,"dur":0},{"ph":"X","cat":"cpu_op","name":"aten::empty","pid":18,"tid":18,"ts":1677894810996188,"dur":1},{"ph":"X","cat":"cpu_op","name":"aten::unsqueeze","pid":18,"tid":18,"ts":1677894810996193,"dur":4},{"ph":"X","cat":"cpu_op","name":"aten::as_strided","pid":18,"tid":18,"ts":1677894810996195,"dur":1},{"ph":"X","cat":"cpu_op","name":"aten::unsqueeze","pid":18,"tid":18,"ts":1677894810996198,"dur":3},{"ph":"X","cat":"cpu_op","name":"aten::as_strided","pid":18,"tid":18,"ts":1677894810996199,"dur":1},{"ph":"X","cat":"cpu_op","name":"aten::add","pid":18,"tid":18,"ts":1677894810996203,"dur":28},{"ph":"X","cat":"cuda_runtime","name":"cudaLaunchKernel","pid":18,"tid":18,"ts":1677894810996219,"dur":9},{"ph":"X","cat":"cpu_op","name":"aten::group_norm","pid":18,"tid":18,"ts":1677894810996249,"dur":67},{"ph":"X","cat":"cpu_op","name":"aten::native_group_norm","pid":18,"tid":18,"ts":1677894810996250,"dur":65},{"ph":"X","cat":"cpu_op","name":"aten::empty","pid":18,"tid":18,"ts":1677894810996254,"dur":5},{"ph":"X","cat":"cpu_op","name":"aten::empty","pid":18,"tid":18,"ts":1677894810996260,"dur":4},{"ph":"X","cat":"cpu_op","name":"aten::empty","pid":18,"tid":18,"ts":1677894810996265,"dur":4},{"ph":"X","cat":"cuda_runtime","name":"cudaLaunchKernel","pid":18,"tid":18,"ts":1677894810996270,"dur":6},{"ph":"X","cat":"cpu_op","name":"aten::empty","pid":18,"tid":18,"ts":1677894810996279,"dur":4},{"ph":"X","cat":"cpu_op","name":"aten::empty","pid":18,"tid":18,"ts":1677894810996284,"dur":4},{"ph":"X","cat":"cuda_runtime","name":"cudaLaunchKernel","pid":18,"tid":18,"ts":1677894810996288,"dur":5},{"ph":"X","cat":"cpu_op","name":"aten::view","pid":18,"tid":18,"ts":1677894810996295,"dur":1},{"ph":"X","cat":"cpu_op","name":"aten::view","pid":18,"tid":18,"ts":1677894810996297,"dur":1},{"ph":"X","cat":"cpu_op","name":"aten::view","pid":18,"tid":18,"ts":1677894810996298,"dur":1},{"ph":"X","cat":"cpu_op","name":"aten::view","pid":18,"tid":18,"ts":1677894810996299,"dur":1},{"ph":"X","cat":"cuda_runtime","name":"cudaLaunchKernel","pid":18,"tid":18,"ts":1677894810996305,"dur":5},{"ph":"X","cat":"cpu_op","name":"aten::zeros","pid":18,"tid":18,"ts":1677894810996403,"dur":4},{"ph":"X","cat":"cpu_op","name":"aten::empty","pid":18,"tid":18,"ts":1677894810996404,"dur":1},{"ph":"X","cat":"cpu_op","name":"aten::zero_","pid":18,"tid":18,"ts":1677894810996406,"dur":1},{"ph":"X","cat":"cpu_op","name":"aten::empty","pid":18,"tid":18,"ts":1677894810996413,"dur":1},{"ph":"X","cat":"cpu_op","name":"aten::silu","pid":18,"tid":18,"ts":1677894810996418,"dur":23},{"ph":"X","cat":"cuda_runtime","name":"cudaLaunchKernel","pid":18,"tid":18,"ts":1677894810996430,"dur":9},{"ph":"X","cat":"cpu_op","name":"aten::zeros","pid":18,"tid":18,"ts":1677894810996525,"dur":4},{"ph":"X","cat":"cpu_op","name":"aten::empty","pid":18,"tid":18,"ts":1677894810996526,"dur":1},{"ph":"X","cat":"cpu_op","name":"aten::zero_","pid":18,"tid":18,"ts":1677894810996528,"dur":0},{"ph":"X","cat":"cpu_op","name":"aten::empty","pid":18,"tid":18,"ts":1677894810996535,"dur":0},{"ph":"X","cat":"cpu_op","name":"aten::conv2d","pid":18,"tid":18,"ts":1677894810996547,"dur":162},{"ph":"X","cat":"cpu_op","name":"aten::convolution","pid":18,"tid":18,"ts":1677894810996548,"dur":161},{"ph":"X","cat":"cpu_op","name":"aten::_convolution","pid":18,"tid":18,"ts":1677894810996550,"dur":158},{"ph":"X","cat":"cpu_op","name":"aten::cudnn_convolution","pid":18,"tid":18,"ts":1677894810996554,"dur":128},{"ph":"X","cat":"cuda_runtime","name":"cudaStreamIsCapturing","pid":18,"tid":18,"ts":1677894810996567,"dur":0},{"ph":"X","cat":"cuda_runtime","name":"cudaStreamGetPriority","pid":18,"tid":18,"ts":1677894810996568,"dur":0},{"ph":"X","cat":"cuda_runtime","name":"cudaDeviceGetStreamPriorityRange","pid":18,"tid":18,"ts":1677894810996569,"dur":0},{"ph":"X","cat":"cpu_op","name":"aten::empty","pid":18,"tid":18,"ts":1677894810996574,"dur":5},{"ph":"X","cat":"cuda_runtime","name":"cudaLaunchKernel","pid":18,"tid":18,"ts":1677894810996632,"dur":10},{"ph":"X","cat":"cuda_runtime","name":"cudaLaunchKernel","pid":18,"tid":18,"ts":1677894810996645,"dur":5},{"ph":"X","cat":"cuda_runtime","name":"cudaMemsetAsync","pid":18,"tid":18,"ts":1677894810996654,"dur":6},{"ph":"X","cat":"cuda_runtime","name":"cudaFuncSetAttribute","pid":18,"tid":18,"ts":1677894810996660,"dur":1},{"ph":"X","cat":"cuda_runtime","name":"cudaFuncSetAttribute","pid":18,"tid":18,"ts":1677894810996661,"dur":0},{"ph":"X","cat":"cuda_runtime","name":"cudaLaunchKernel","pid":18,"tid":18,"ts":1677894810996662,"dur":5},{"ph":"X","cat":"cuda_runtime","name":"cudaLaunchKernel","pid":18,"tid":18,"ts":1677894810996670,"dur":5},{"ph":"X","cat":"cpu_op","name":"aten::reshape","pid":18,"tid":18,"ts":1677894810996685,"dur":5},{"ph":"X","cat":"cpu_op","name":"aten::_reshape_alias","pid":18,"tid":18,"ts":1677894810996688,"dur":1},{"ph":"X","cat":"cpu_op","name":"aten::add_","pid":18,"tid":18,"ts":1677894810996690,"dur":17},{"ph":"X","cat":"cuda_runtime","name":"cudaLaunchKernel","pid":18,"tid":18,"ts":1677894810996699,"dur":6},{"ph":"X","cat":"cpu_op","name":"aten::conv2d","pid":18,"tid":18,"ts":1677894810996727,"dur":104},{"ph":"X","cat":"cpu_op","name":"aten::convolution","pid":18,"tid":18,"ts":1677894810996728,"dur":103},{"ph":"X","cat":"cpu_op","name":"aten::_convolution","pid":18,"tid":18,"ts":1677894810996731,"dur":99},{"ph":"X","cat":"cpu_op","name":"aten::cudnn_convolution","pid":18,"tid":18,"ts":1677894810996733,"dur":75},{"ph":"X","cat":"cuda_runtime","name":"cudaStreamIsCapturing","pid":18,"tid":18,"ts":1677894810996745,"dur":0},{"ph":"X","cat":"cuda_runtime","name":"cudaStreamGetPriority","pid":18,"tid":18,"ts":1677894810996746,"dur":0},{"ph":"X","cat":"cuda_runtime","name":"cudaDeviceGetStreamPriorityRange","pid":18,"tid":18,"ts":1677894810996746,"dur":0},{"ph":"X","cat":"cpu_op","name":"aten::empty","pid":18,"tid":18,"ts":1677894810996751,"dur":4},{"ph":"X","cat":"cuda_runtime","name":"cudaOccupancyMaxActiveBlocksPerMultiprocessorWithFlags","pid":18,"tid":18,"ts":1677894810996784,"dur":1},{"ph":"X","cat":"cuda_runtime","name":"cudaOccupancyMaxActiveBlocksPerMultiprocessorWithFlags","pid":18,"tid":18,"ts":1677894810996786,"dur":0},{"ph":"X","cat":"cuda_runtime","name":"cudaFuncSetAttribute","pid":18,"tid":18,"ts":1677894810996787,"dur":0},{"ph":"X","cat":"cuda_runtime","name":"cudaLaunchKernel","pid":18,"tid":18,"ts":1677894810996789,"dur":8},{"ph":"X","cat":"cuda_runtime","name":"cudaLaunchKernel","pid":18,"tid":18,"ts":1677894810996798,"dur":4},{"ph":"X","cat":"cpu_op","name":"aten::reshape","pid":18,"tid":18,"ts":1677894810996810,"dur":4},{"ph":"X","cat":"cpu_op","name":"aten::_reshape_alias","pid":18,"tid":18,"ts":1677894810996813,"dur":1},{"ph":"X","cat":"cpu_op","name":"aten::add_","pid":18,"tid":18,"ts":1677894810996815,"dur":14},{"ph":"X","cat":"cuda_runtime","name":"cudaLaunchKernel","pid":18,"tid":18,"ts":1677894810996822,"dur":5},{"ph":"X","cat":"kernel","name":"void at::native::elementwise_kernel<128, 2, at::native::gpu_kernel_impl<at::native::direct_copy_kernel_cuda(at::TensorIteratorBase&)::{lambda()#2}::operator()() const::{lambda()#14}::operator()() const::{lambda(float)#1}>(at::TensorIteratorBase&, at::native::direct_copy_kernel_cuda(at::TensorIteratorBase&)::{lambda()#2}::operator()() const::{lambda()#14}::operator()() const::{lambda(float)#1} const&)::{lambda(int)#1}>(int, at::native::gpu_kernel_impl<at::native::direct_copy_kernel_cuda(at::TensorIteratorBase&)::{lambda()#2}::operator()() const::{lambda()#14}::operator()() const::{lambda(float)#1}>(at::TensorIteratorBase&, at::native::direct_copy_kernel_cuda(at::TensorIteratorBase&)::{lambda()#2}::operator()() const::{lambda()#14}::operator()() const::{lambda(float)#1} const&)::{lambda(int)#1})","pid":0,"tid":7,"ts":1677894810995344,"dur":2},{"ph":"X","cat":"kernel","name":"void at::native::(anonymous namespace)::RowwiseMomentsCUDAKernel<float>(long, float, float const*, float*, float*)","pid":0,"tid":7,"ts":1677894810995375,"dur":4},{"ph":"X","cat":"kernel","name":"void at::native::(anonymous namespace)::ComputeFusedParamsCUDAKernel<float>(long, long, long, float const*, float const*, float const*, float const*, at::AccumulateType<float, true>::type*, at::AccumulateType<float, true>::type*)","pid":0,"tid":7,"ts":1677894810995390,"dur":2},{"ph":"X","cat":"kernel","name":"void at::native::elementwise_kernel<128, 2, at::native::gpu_kernel_impl<at::native::(anonymous namespace)::GroupNormKernelImplInternal<float>(at::Tensor const&, at::Tensor const&, at::Tensor const&, long, long, long, long, float, at::Tensor&, at::Tensor&, at::Tensor&)::{lambda(float, float, float)#2}>(at::TensorIteratorBase&, at::native::(anonymous namespace)::GroupNormKernelImplInternal<float>(at::Tensor const&, at::Tensor const&, at::Tensor const&, long, long, long, long, float, at::Tensor&, at::Tensor&, at::Tensor&)::{lambda(float, float, float)#2} const&)::{lambda(int)#1}>(int, at::native::gpu_kernel_impl<at::native::(anonymous namespace)::GroupNormKernelImplInternal<float>(at::Tensor const&, at::Tensor const&, at::Tensor const&, long, long, long, long, float, at::Tensor&, at::Tensor&, at::Tensor&)::{lambda(float, float, float)#2}>(at::TensorIteratorBase&, at::native::(anonymous namespace)::GroupNormKernelImplInternal<float>(at::Tensor const&, at::Tensor const&, at::Tensor const&, long, long, long, long, float, at::Tensor&, at::Tensor&, at::Tensor&)::{lambda(float, float, float)#2} const&)::{lambda(int)#1})","pid":0,"tid":7,"ts":1677894810995406,"dur":2},{"ph":"X","cat":"kernel","name":"void at::native::vectorized_elementwise_kernel<4, at::native::(anonymous namespace)::silu_kernel(at::TensorIteratorBase&)::{lambda()#1}::operator()() const::{lambda()#4}::operator()() const::{lambda(float)#1}, at::detail::Array<char*, 2> >(int, at::native::(anonymous namespace)::silu_kernel(at::TensorIteratorBase&)::{lambda()#1}::operator()() const::{lambda()#4}::operator()() const::{lambda(float)#1}, at::detail::Array<char*, 2>)","pid":0,"tid":7,"ts":1677894810995536,"dur":2},{"ph":"X","cat":"kernel","name":"void cudnn::ops::nchwToNhwcKernel<float, float, float, false, true, (cudnnKernelDataType_t)2>(cudnn::ops::nchw2nhwc_params_t<float>, float const*, float*)","pid":0,"tid":7,"ts":1677894810995735,"dur":2},{"ph":"X","cat":"kernel","name":"void cudnn::ops::nchwToNhwcKernel<float, float, float, false, true, (cudnnKernelDataType_t)2>(cudnn::ops::nchw2nhwc_params_t<float>, float const*, float*)","pid":0,"tid":7,"ts":1677894810995742,"dur":74},{"ph":"X","cat":"kernel","name":"void cutlass_cudnn::Kernel<cutlass_tensorop_s1688fprop_optimized_tf32_64x64_16x10_nhwc>(cutlass_tensorop_s1688fprop_optimized_tf32_64x64_16x10_nhwc::Params)","pid":0,"tid":7,"ts":1677894810995818,"dur":107},{"ph":"X","cat":"kernel","name":"void cudnn::ops::nhwcToNchwKernel<float, float, float, true, false, (cudnnKernelDataType_t)0>(cudnn::ops::nhwc2nchw_params_t<float>, float const*, float*)","pid":0,"tid":7,"ts":1677894810995926,"dur":3},{"ph":"X","cat":"kernel","name":"void at::native::elementwise_kernel<128, 2, at::native::gpu_kernel_impl<at::native::CUDAFunctor_add<float> >(at::TensorIteratorBase&, at::native::CUDAFunctor_add<float> const&)::{lambda(int)#1}>(int, at::native::gpu_kernel_impl<at::native::CUDAFunctor_add<float> >(at::TensorIteratorBase&, at::native::CUDAFunctor_add<float> const&)::{lambda(int)#1})","pid":0,"tid":7,"ts":1677894810995930,"dur":3},{"ph":"X","cat":"kernel","name":"void at::native::vectorized_elementwise_kernel<4, at::native::(anonymous namespace)::silu_kernel(at::TensorIteratorBase&)::{lambda()#1}::operator()() const::{lambda()#4}::operator()() const::{lambda(float)#1}, at::detail::Array<char*, 2> >(int, at::native::(anonymous namespace)::silu_kernel(at::TensorIteratorBase&)::{lambda()#1}::operator()() const::{lambda()#4}::operator()() const::{lambda(float)#1}, at::detail::Array<char*, 2>)","pid":0,"tid":7,"ts":1677894810995934,"dur":2},{"ph":"X","cat":"kernel","name":"std::enable_if<!(false), void>::type internal::gemvx::kernel<int, int, float, float, float, float, false, true, true, false, 6, false, cublasGemvParams<cublasGemvTensorStridedBatched<float const>, cublasGemvTensorStridedBatched<float const>, cublasGemvTensorStridedBatched<float>, float> >(cublasGemvParams<cublasGemvTensorStridedBatched<float const>, cublasGemvTensorStridedBatched<float const>, cublasGemvTensorStridedBatched<float>, float>)","pid":0,"tid":7,"ts":1677894810996076,"dur":12},{"ph":"X","cat":"kernel","name":"void splitKreduce_kernel<32, 16, int, float, float, float, float, true, false, false>(cublasSplitKParams<float>, float const*, float const*, float*, float const*, float const*, float const*, float const*, float*, void*, long, float*, int*)","pid":0,"tid":7,"ts":1677894810996089,"dur":2},{"ph":"X","cat":"kernel","name":"void epilogue::impl::globalKernel<8, 32, float, float, float, true, true>(int, int, long, float*, cublasLtEpilogue_t, int, float*, long, void*, long, long, long, float*, long, int*)","pid":0,"tid":7,"ts":1677894810996092,"dur":2},{"ph":"X","cat":"kernel","name":"void at::native::elementwise_kernel<128, 2, at::native::gpu_kernel_impl<at::native::CUDAFunctor_add<float> >(at::TensorIteratorBase&, at::native::CUDAFunctor_add<float> const&)::{lambda(int)#1}>(int, at::native::gpu_kernel_impl<at::native::CUDAFunctor_add<float> >(at::TensorIteratorBase&, at::native::CUDAFunctor_add<float> const&)::{lambda(int)#1})","pid":0,"tid":7,"ts":1677894810996229,"dur":2},{"ph":"X","cat":"kernel","name":"void at::native::(anonymous namespace)::RowwiseMomentsCUDAKernel<float>(long, float, float const*, float*, float*)","pid":0,"tid":7,"ts":1677894810996278,"dur":4},{"ph":"X","cat":"kernel","name":"void at::native::(anonymous namespace)::ComputeFusedParamsCUDAKernel<float>(long, long, long, float const*, float const*, float const*, float const*, at::AccumulateType<float, true>::type*, at::AccumulateType<float, true>::type*)","pid":0,"tid":7,"ts":1677894810996294,"dur":2},{"ph":"X","cat":"kernel","name":"void at::native::elementwise_kernel<128, 2, at::native::gpu_kernel_impl<at::native::(anonymous namespace)::GroupNormKernelImplInternal<float>(at::Tensor const&, at::Tensor const&, at::Tensor const&, long, long, long, long, float, at::Tensor&, at::Tensor&, at::Tensor&)::{lambda(float, float, float)#2}>(at::TensorIteratorBase&, at::native::(anonymous namespace)::GroupNormKernelImplInternal<float>(at::Tensor const&, at::Tensor const&, at::Tensor const&, long, long, long, long, float, at::Tensor&, at::Tensor&, at::Tensor&)::{lambda(float, float, float)#2} const&)::{lambda(int)#1}>(int, at::native::gpu_kernel_impl<at::native::(anonymous namespace)::GroupNormKernelImplInternal<float>(at::Tensor const&, at::Tensor const&, at::Tensor const&, long, long, long, long, float, at::Tensor&, at::Tensor&, at::Tensor&)::{lambda(float, float, float)#2}>(at::TensorIteratorBase&, at::native::(anonymous namespace)::GroupNormKernelImplInternal<float>(at::Tensor const&, at::Tensor const&, at::Tensor const&, long, long, long, long, float, at::Tensor&, at::Tensor&, at::Tensor&)::{lambda(float, float, float)#2} const&)::{lambda(int)#1})","pid":0,"tid":7,"ts":1677894810996311,"dur":2},{"ph":"X","cat":"kernel","name":"void at::native::vectorized_elementwise_kernel<4, at::native::(anonymous namespace)::silu_kernel(at::TensorIteratorBase&)::{lambda()#1}::operator()() const::{lambda()#4}::operator()() const::{lambda(float)#1}, at::detail::Array<char*, 2> >(int, at::native::(anonymous namespace)::silu_kernel(at::TensorIteratorBase&)::{lambda()#1}::operator()() const::{lambda()#4}::operator()() const::{lambda(float)#1}, at::detail::Array<char*, 2>)","pid":0,"tid":7,"ts":1677894810996439,"dur":2},{"ph":"X","cat":"kernel","name":"void cudnn::ops::nchwToNhwcKernel<float, float, float, false, true, (cudnnKernelDataType_t)2>(cudnn::ops::nchw2nhwc_params_t<float>, float const*, float*)","pid":0,"tid":7,"ts":1677894810996644,"dur":2},{"ph":"X","cat":"kernel","name":"void cudnn::ops::nchwToNhwcKernel<float, float, float, false, true, (cudnnKernelDataType_t)2>(cudnn::ops::nchw2nhwc_params_t<float>, float const*, float*)","pid":0,"tid":7,"ts":1677894810996651,"dur":148},{"ph":"X","cat":"gpu_memset","name":"Memset (Device)","pid":0,"tid":7,"ts":1677894810996800,"dur":0},{"ph":"X","cat":"kernel","name":"sm80_xmma_fprop_implicit_gemm_indexed_tf32f32_tf32f32_f32_nhwckrsc_nhwc_tilesize128x128x16_stage4_warpsize2x2x1_g1_tensor16x8x8_execute_kernel_cudnn","pid":0,"tid":7,"ts":1677894810996803,"dur":161},{"ph":"X","cat":"kernel","name":"void cudnn::ops::nhwcToNchwKernel<float, float, float, true, false, (cudnnKernelDataType_t)0>(cudnn::ops::nhwc2nchw_params_t<float>, float const*, float*)","pid":0,"tid":7,"ts":1677894810996965,"dur":3},{"ph":"X","cat":"kernel","name":"void at::native::elementwise_kernel<128, 2, at::native::gpu_kernel_impl<at::native::CUDAFunctor_add<float> >(at::TensorIteratorBase&, at::native::CUDAFunctor_add<float> const&)::{lambda(int)#1}>(int, at::native::gpu_kernel_impl<at::native::CUDAFunctor_add<float> >(at::TensorIteratorBase&, at::native::CUDAFunctor_add<float> const&)::{lambda(int)#1})","pid":0,"tid":7,"ts":1677894810996969,"dur":3},{"ph":"X","cat":"kernel","name":"void cutlass::Kernel<cutlass_80_tensorop_s1688gemm_64x64_16x6_tn_align4>(cutlass_80_tensorop_s1688gemm_64x64_16x6_tn_align4::Params)","pid":0,"tid":7,"ts":1677894810996973,"dur":9},{"ph":"X","cat":"kernel","name":"void splitKreduce_kernel<32, 16, int, float, float, float, float, true, false, false>(cublasSplitKParams<float>, float const*, float const*, float*, float const*, float const*, float const*, float const*, float*, void*, long, float*, int*)","pid":0,"tid":7,"ts":1677894810996983,"dur":2},{"ph":"X","cat":"kernel","name":"void at::native::elementwise_kernel<128, 2, at::native::gpu_kernel_impl<at::native::CUDAFunctor_add<float> >(at::TensorIteratorBase&, at::native::CUDAFunctor_add<float> const&)::{lambda(int)#1}>(int, at::native::gpu_kernel_impl<at::native::CUDAFunctor_add<float> >(at::TensorIteratorBase&, at::native::CUDAFunctor_add<float> const&)::{lambda(int)#1})","pid":0,"tid":7,"ts":1677894810996986,"dur":3}]