[{"ph":"X","cat":"cpu_op","name":"aten::zeros","pid":18,"tid":18,"ts":1677894810911524,"dur":4},{"ph":"X","cat":"cpu_op","name":"aten::empty","pid":18,"tid":18,"ts":1677894810911525,"dur":1},{"ph":"X","cat":"cpu_op","name":"aten::zero_","pid":18,"tid":18,"ts":1677894810911527,"dur":0},{"ph":"X","cat":"cpu_op","name":"aten::empty","pid":18,"tid":18,"ts":1677894810911533,"dur":1},{"ph":"X","cat":"cpu_op","name":"aten::conv2d","pid":18,"tid":18,"ts":1677894810911547,"dur":160},{"ph":"X","cat":"cpu_op","name":"aten::convolution","pid":18,"tid":18,"ts":1677894810911548,"dur":159},{"ph":"X","cat":"cpu_op","name":"aten::_convolution","pid":18,"tid":18,"ts":1677894810911550,"dur":156},{"ph":"X","cat":"cpu_op","name":"aten::cudnn_convolution","pid":18,"tid":18,"ts":1677894810911553,"dur":126},{"ph":"X","cat":"cuda_runtime","name":"cudaStreamIsCapturing","pid":18,"tid":18,"ts":1677894810911567,"dur":0},{"ph":"X","cat":"cuda_runtime","name":"cudaStreamGetPriority","pid":18,"tid":18,"ts":1677894810911568,"dur":0},{"ph":"X","cat":"cuda_runtime","name":"cudaDeviceGetStreamPriorityRange","pid":18,"tid":18,"ts":1677894810911569,"dur":0},{"ph":"X","cat":"cpu_op","name":"aten::empty","pid":18,"tid":18,"ts":1677894810911574,"dur":4},{"ph":"X","cat":"cuda_runtime","name":"cudaStreamWaitEvent","pid":18,"tid":18,"ts":1677894810911606,"dur":1},{"ph":"X","cat":"cuda_runtime","name":"cudaStreamWaitEvent","pid":18,"tid":18,"ts":1677894810911607,"dur":0},{"ph":"X","cat":"cuda_runtime","name":"cudaStreamWaitEvent","pid":18,"tid":18,"ts":1677894810911608,"dur":0},{"ph":"X","cat":"cuda_runtime","name":"cudaStreamWaitEvent","pid":18,"tid":18,"ts":1677894810911609,"dur":0},{"ph":"X","cat":"cuda_runtime","name":"cudaLaunchKernel","pid":18,"tid":18,"ts":1677894810911611,"dur":10},{"ph":"X","cat":"cuda_runtime","name":"cudaLaunchKernel","pid":18,"tid":18,"ts":1677894810911622,"dur":5},{"ph":"X","cat":"cuda_runtime","name":"cudaLaunchKernel","pid":18,"tid":18,"ts":1677894810911633,"dur":6},{"ph":"X","cat":"cuda_runtime","name":"cudaLaunchKernel","pid":18,"tid":18,"ts":1677894810911643,"dur":5},{"ph":"X","cat":"cuda_runtime","name":"cudaLaunchKernel","pid":18,"tid":18,"ts":1677894810911651,"dur":5},{"ph":"X","cat":"cuda_runtime","name":"cudaLaunchKernel","pid":18,"tid":18,"ts":1677894810911659,"dur":5},{"ph":"X","cat":"cuda_runtime","name":"cudaStreamWaitEvent","pid":18,"tid":18,"ts":1677894810911667,"dur":0},{"ph":"X","cat":"cuda_runtime","name":"cudaStreamWaitEvent","pid":18,"tid":18,"ts":1677894810911669,"dur":0},{"ph":"X","cat":"cuda_runtime","name":"cudaStreamWaitEvent","pid":18,"tid":18,"ts":1677894810911670,"dur":0},{"ph":"X","cat":"cuda_runtime","name":"cudaStreamWaitEvent","pid":18,"tid":18,"ts":1677894810911672,"dur":0},{"ph":"X","cat":"cpu_op","name":"aten::reshape","pid":18,"tid":18,"ts":1677894810911681,"dur":5},{"ph":"X","cat":"cpu_op","name":"aten::_reshape_alias","pid":18,"tid":18,"ts":1677894810911684,"dur":2},{"ph":"X","cat":"cpu_op","name":"aten::add_","pid":18,"tid":18,"ts":1677894810911687,"dur":18},{"ph":"X","cat":"cuda_runtime","name":"cudaLaunchKernel","pid":18,"tid":18,"ts":1677894810911696,"dur":7},{"ph":"X","cat":"kernel","name":"void cudnn::cnn::kern_precompute_indices<false>(int*, int, int, int, int, int)","pid":0,"tid":7,"ts":1677894810911622,"dur":3},{"ph":"X","cat":"kernel","name":"void precomputed_convolve_sgemm<float, 1024, 5, 5, 4, 3, 3, 1, false>(int, int, int, float const*, int, float*, float const*, kernel_conv_params, unsigned long long, int, float, float, int, bool, float const*, float const*, int*)","pid":0,"tid":7,"ts":1677894810911629,"dur":1231},{"ph":"X","cat":"kernel","name":"void at::native::elementwise_kernel<128, 2, at::native::gpu_kernel_impl<at::native::CUDAFunctor_add<float> >(at::TensorIteratorBase&, at::native::CUDAFunctor_add<float> const&)::{lambda(int)#1}>(int, at::native::gpu_kernel_impl<at::native::CUDAFunctor_add<float> >(at::TensorIteratorBase&, at::native::CUDAFunctor_add<float> const&)::{lambda(int)#1})","pid":0,"tid":7,"ts":1677894810913428,"dur":3},{"ph":"X","cat":"kernel","name":"void implicit_convolve_sgemm<float, float, 128, 5, 5, 3, 3, 3, 1, false, false, true>(int, int, int, float const*, int, float*, float const*, kernel_conv_params, unsigned long long, int, float, float, int, float const*, float const*, bool, int, int)","pid":0,"tid":13,"ts":1677894810911641,"dur":1680},{"ph":"X","cat":"kernel","name":"void implicit_convolve_sgemm<float, float, 128, 5, 5, 3, 3, 3, 1, false, false, true>(int, int, int, float const*, int, float*, float const*, kernel_conv_params, unsigned long long, int, float, float, int, float const*, float const*, bool, int, int)","pid":0,"tid":14,"ts":1677894810911649,"dur":1684},{"ph":"X","cat":"kernel","name":"void implicit_convolve_sgemm<float, float, 128, 5, 5, 3, 3, 3, 1, false, false, true>(int, int, int, float const*, int, float*, float const*, kernel_conv_params, unsigned long long, int, float, float, int, float const*, float const*, bool, int, int)","pid":0,"tid":15,"ts":1677894810911658,"dur":1676},{"ph":"X","cat":"kernel","name":"void implicit_convolve_sgemm<float, float, 128, 5, 5, 3, 3, 3, 1, false, false, true>(int, int, int, float const*, int, float*, float const*, kernel_conv_params, unsigned long long, int, float, float, int, float const*, float const*, bool, int, int)","pid":0,"tid":16,"ts":1677894810911666,"dur":1761}]